{
	"name": "101_PL_Load_Customer",
	"properties": {
		"description": "Pipeline to Load Customer information from Blob storage ",
		"activities": [
			{
				"name": "Load Customers",
				"description": "Load Customers from CSV file in to SQL Database",
				"type": "Copy",
				"dependsOn": [
					{
						"activity": "Truncate Taerget Table",
						"dependencyConditions": [
							"Succeeded"
						]
					}
				],
				"policy": {
					"timeout": "7.00:00:00",
					"retry": 0,
					"retryIntervalInSeconds": 30,
					"secureOutput": false,
					"secureInput": false
				},
				"userProperties": [],
				"typeProperties": {
					"source": {
						"type": "DelimitedTextSource",
						"storeSettings": {
							"type": "AzureBlobStorageReadSettings",
							"recursive": true,
							"enablePartitionDiscovery": false
						},
						"formatSettings": {
							"type": "DelimitedTextReadSettings"
						}
					},
					"sink": {
						"type": "AzureSqlSink",
						"writeBehavior": "insert",
						"sqlWriterUseTableLock": true,
						"disableMetricsCollection": false
					},
					"enableStaging": false,
					"translator": {
						"type": "TabularTranslator",
						"mappings": [
							{
								"source": {
									"name": "id",
									"type": "String",
									"physicalType": "String"
								},
								"sink": {
									"name": "id",
									"type": "Int64",
									"physicalType": "bigint"
								}
							},
							{
								"source": {
									"name": "first_name",
									"type": "String",
									"physicalType": "String"
								},
								"sink": {
									"name": "first_name",
									"type": "String",
									"physicalType": "varchar"
								}
							},
							{
								"source": {
									"name": "last_name",
									"type": "String",
									"physicalType": "String"
								},
								"sink": {
									"name": "last_name",
									"type": "String",
									"physicalType": "varchar"
								}
							},
							{
								"source": {
									"name": "email",
									"type": "String",
									"physicalType": "String"
								},
								"sink": {
									"name": "email",
									"type": "String",
									"physicalType": "varchar"
								}
							},
							{
								"source": {
									"name": "dob",
									"type": "String",
									"physicalType": "String"
								},
								"sink": {
									"name": "dob",
									"type": "String",
									"physicalType": "varchar"
								}
							},
							{
								"source": {
									"name": "ip_address",
									"type": "String",
									"physicalType": "String"
								},
								"sink": {
									"name": "ip_address",
									"type": "String",
									"physicalType": "varchar"
								}
							}
						],
						"typeConversion": true,
						"typeConversionSettings": {
							"allowDataTruncation": true,
							"treatBooleanAsNumber": false,
							"dateTimeFormat": "dd/MM/yyyy"
						}
					}
				},
				"inputs": [
					{
						"referenceName": "DS_ABLB_CustomerCSV",
						"type": "DatasetReference"
					}
				],
				"outputs": [
					{
						"referenceName": "DS_SQL_Customer",
						"type": "DatasetReference"
					}
				]
			},
			{
				"name": "Truncate Taerget Table",
				"type": "Script",
				"dependsOn": [],
				"policy": {
					"timeout": "7.00:00:00",
					"retry": 0,
					"retryIntervalInSeconds": 30,
					"secureOutput": false,
					"secureInput": false
				},
				"userProperties": [],
				"linkedServiceName": {
					"referenceName": "LS_SQL_ADFCustomer",
					"type": "LinkedServiceReference"
				},
				"typeProperties": {
					"scripts": [
						{
							"type": "NonQuery",
							"text": "Truncate Table dbo.adf_Customer;"
						}
					],
					"logSettings": {
						"logDestination": "ActivityOutput"
					}
				}
			}
		],
		"folder": {
			"name": "ADF Pipeline/100_PL_Customer"
		},
		"annotations": [
			"Navaneethakrishnan Thangaraj"
		],
		"lastPublishTime": "2022-06-27T03:22:36Z"
	},
	"type": "Microsoft.DataFactory/factories/pipelines"
}